{"chapter":135,"verses":[{"verse":1,"text":"Praise ye Jehovah."},{"verse":2,"text":"Ye that stand in the house of Jehovah,"},{"verse":3,"text":"Praise ye Jehovah; for Jehovah is good:"},{"verse":4,"text":"For Jehovah hath chosen Jacob unto himself,"},{"verse":5,"text":"For I know that Jehovah is great,"},{"verse":6,"text":"Whatsoever Jehovah pleased, that hath he done,"},{"verse":7,"text":"Who causeth the vapors to ascend from the ends of the earth;"},{"verse":8,"text":"Who smote the first-born of Egypt,"},{"verse":9,"text":"Who sent signs and wonders into the midst of thee, O Egypt,"},{"verse":10,"text":"Who smote many nations,"},{"verse":11,"text":"Sihon king of the Amorites,"},{"verse":12,"text":"And gave their land for a heritage,"},{"verse":13,"text":"Thy name, O Jehovah, endureth for ever;"},{"verse":14,"text":"For Jehovah will judge his people,"},{"verse":15,"text":"The idols of the nations are silver and gold,"},{"verse":16,"text":"They have mouths, but they speak not;"},{"verse":17,"text":"They have ears, but they hear not;"},{"verse":18,"text":"They that make them shall be like unto them;"},{"verse":19,"text":"O house of Israel, bless ye Jehovah:"},{"verse":20,"text":"O house of Levi, bless ye Jehovah:"},{"verse":21,"text":"Blessed be Jehovah out of Zion,"}]}